[
    {
        "id": 0,
        "name": "Unai",
        "last_name": "Simón",
        "number": 1,
        "height": 190,
        "country": "España",
        "position": "Portero",
        "birthday": "11-06-1997",
        "photo": "https://cdn.athletic-club.eus/imagenes/fotofichas/M/unai-simon-mendibil_M.png?v=3.0",
        "team": 0
    },
    {
        "id": 1,
        "name": "Julen",
        "last_name": "Agirrezabala",
        "number": 13,
        "height": 187,
        "country": "España",
        "position": "Portero",
        "birthday": "26-12-2000",
        "photo": "https://cdn.athletic-club.eus/imagenes/fotofichas/M/julen-agirrezabala-astulez_M.png",
        "team": 0
    },
    {
        "id": 2,
        "name": "Alejandro",
        "last_name": "Padilla",
        "number": 26,
        "height": 190,
        "country": "México",
        "position": "Portero",
        "birthday": "01-09-2003",
        "photo": "https://cdn.athletic-club.eus/imagenes/fotofichas/M/alex-padilla-perez_M.png",
        "team": 0
    },
    {
        "id": 3,
        "name": "Oier",
        "last_name": "Gastesi",
        "number": 34,
        "height": 190,
        "country": "España",
        "position": "Portero",
        "birthday": "30-10-2003",
        "photo": "https://cdn.athletic-club.eus/imagenes/fotofichas/M/oier-gastesi-serrano_M.png?v=1.0",
        "team": 0
    },
    {
        "id": 4,
        "name": "Andoni",
        "last_name": "Gorosabel",
        "number": 2,
        "height": 174,
        "country": "España",
        "position": "Defensa",
        "birthday": "04-08-1996",
        "photo": "https://cdn.athletic-club.eus/imagenes/fotofichas/M/andoni-gorosabel-espinosa_M.png",
        "team": 0
    },
    {
        "id": 5,
        "name": "Daniel",
        "last_name": "Vivian",
        "number": 3,
        "height": 183,
        "country": "España",
        "position": "Defensa",
        "birthday": "05-07-1999",
        "photo": "https://cdn.athletic-club.eus/imagenes/fotofichas/M/daniel-vivian-moreno_M.png",
        "team": 0
    },
    {
        "id": 6,
        "name": "Aitor",
        "last_name": "Paredes",
        "number": 4,
        "height": 186,
        "country": "España",
        "position": "Defensa",
        "birthday": "29-04-2000",
        "photo": "https://cdn.athletic-club.eus/imagenes/fotofichas/M/aitor-paredes-casamichana_M.png",
        "team": 0
    },
    {
        "id": 7,
        "name": "Yeray",
        "last_name": "Álvarez",
        "number": 5,
        "height": 182,
        "country": "España",
        "position": "Defensa",
        "birthday": "24-01-1995",
        "photo": "https://cdn.athletic-club.eus/imagenes/fotofichas/M/yeray-alvarez-lopez_M.png",
        "team": 0
    },
    {
        "id": 8,
        "name": "Unai",
        "last_name": "Núñez",
        "number": 14,
        "height": 186,
        "country": "España",
        "position": "Defensa",
        "birthday": "30-01-1997",
        "photo": "https://cdn.athletic-club.eus/imagenes/fotofichas/M/unai-nunez-gestoso_M.png?v=2.0",
        "team": 0
    },
    {
        "id": 9,
        "name": "Íñigo",
        "last_name": "Lekue",
        "number": 15,
        "height": 180,
        "country": "España",
        "position": "Defensa",
        "birthday": "04-05-1993",
        "photo": "https://cdn.athletic-club.eus/imagenes/fotofichas/M/inigo-lekue-martinez_M.png",
        "team": 0
    },
    {
        "id": 10,
        "name": "Yuri",
        "last_name": "Berchiche",
        "number": 17,
        "height": 181,
        "country": "España",
        "position": "Defensa",
        "birthday": "10-02-1990",
        "photo": "https://cdn.athletic-club.eus/imagenes/fotofichas/M/yuri-berchiche-izeta_M.png",
        "team": 0
    },
    {
        "id": 11,
        "name": "Óscar",
        "last_name": "De Marcos",
        "number": 18,
        "height": 182,
        "country": "España",
        "position": "Defensa",
        "birthday": "14-04-1989",
        "photo": "https://cdn.athletic-club.eus/imagenes/fotofichas/M/oscar-de-marcos-arana_M.png",
        "team": 0
    },
    {
        "id": 12,
        "name": "Mikel",
        "last_name": "Vesga",
        "number": 6,
        "height": 191,
        "country": "España",
        "position": "Mediocampista",
        "birthday": "08-04-1993",
        "photo": "https://cdn.athletic-club.eus/imagenes/fotofichas/M/mikel-vesga-arruti_M.png",
        "team": 0
    },
    {
        "id": 13,
        "name": "Oihan",
        "last_name": "Sancet",
        "number": 8,
        "height": 188,
        "country": "España",
        "position": "Mediocampista",
        "birthday": "25-04-2000",
        "photo": "https://cdn.athletic-club.eus/imagenes/fotofichas/M/oihan-sancet-tirapu_M.png",
        "team": 0
    },
    {
        "id": 14,
        "name": "Íñigo",
        "last_name": "Ruíz De Galarreta",
        "number": 16,
        "height": 175,
        "country": "España",
        "position": "Mediocampista",
        "birthday": "06-08-1993",
        "photo": "https://cdn.athletic-club.eus/imagenes/fotofichas/M/inigo-ruiz-de-galarreta-etxeberria_M.png",
        "team": 0
    },
    {
        "id": 15,
        "name": "Unai",
        "last_name": "Gómez",
        "number": 20,
        "height": 183,
        "country": "España",
        "position": "Mediocampista",
        "birthday": "25-05-2003",
        "photo": "https://cdn.athletic-club.eus/imagenes/fotofichas/M/unai-gomez-etxebarria_M.png",
        "team": 0
    },
    {
        "id": 16,
        "name": "Ander",
        "last_name": "Herrera",
        "number": 21,
        "height": 182,
        "country": "España",
        "position": "Mediocampista",
        "birthday": "14-08-1989",
        "photo": "https://cdn.athletic-club.eus/imagenes/fotofichas/M/ander-herrera-aguera_M.png",
        "team": 0
    },
    {
        "id": 17,
        "name": "Mikel",
        "last_name": "Jaureguizar",
        "number": 23,
        "height": 177,
        "country": "España",
        "position": "Mediocampista",
        "birthday": "13-11-2003",
        "photo": "https://cdn.athletic-club.eus/imagenes/fotofichas/M/mikel-jauregizar-alboniga_M.png?v=1.0",
        "team": 0
    },
    {
        "id": 18,
        "name": "Beñat",
        "last_name": "Prados",
        "number": 24,
        "height": 180,
        "country": "España",
        "position": "Mediocampista",
        "birthday": "08-02-2001",
        "photo": "https://cdn.athletic-club.eus/imagenes/fotofichas/M/benat-prados-diaz_M.png",
        "team": 0
    },
    {
        "id": 19,
        "name": "Adama",
        "last_name": "Boiro",
        "number": 32,
        "height": 183,
        "country": "España",
        "position": "Mediocampista",
        "birthday": "22-06-2002",
        "photo": "https://cdn.athletic-club.eus/imagenes/fotofichas/M/adama-boiro-boiro_M.png",
        "team": 0
    },
    {
        "id": 20,
        "name": "Álex",
        "last_name": "Berenguer",
        "number": 7,
        "height": 175,
        "country": "España",
        "position": "Delantero",
        "birthday": "04-07-1995",
        "photo": "https://cdn.athletic-club.eus/imagenes/fotofichas/M/alejandro-berenguer-remiro_M.png?v=2.0",
        "team": 0
    },
    {
        "id": 21,
        "name": "Iñaki",
        "last_name": "Williams",
        "number": 9,
        "height": 186,
        "country": "Ghana",
        "position": "Delantero",
        "birthday": "15-06-1994",
        "photo": "https://cdn.athletic-club.eus/imagenes/fotofichas/M/inaki-williams-arthuer_M.png?v=1.0",
        "team": 0
    },
    {
        "id": 22,
        "name": "Nicholas",
        "last_name": "Williams",
        "number": 10,
        "height": 181,
        "country": "España",
        "position": "Delantero",
        "birthday": "12-07-2002",
        "photo": "https://cdn.athletic-club.eus/imagenes/fotofichas/M/nicholas-williams-arthuer_M.png",
        "team": 0
    },
    {
        "id": 23,
        "name": "Álvaro",
        "last_name": "Djaló",
        "number": 11,
        "height": 175,
        "country": "España",
        "position": "Delantero",
        "birthday": "16-08-1999",
        "photo": "https://cdn.athletic-club.eus/imagenes/fotofichas/M/alvaro-djalo-dias-fernandes_M.png",
        "team": 0
    },
    {
        "id": 24,
        "name": "Gorka",
        "last_name": "Guruzeta",
        "number": 12,
        "height": 188,
        "country": "España",
        "position": "Delantero",
        "birthday": "12-09-1996",
        "photo": "https://cdn.athletic-club.eus/imagenes/fotofichas/M/gorka-guruzeta-rodriguez_M.png",
        "team": 0
    },
    {
        "id": 25,
        "name": "Javier",
        "last_name": "Martón",
        "number": 19,
        "height": 183,
        "country": "España",
        "position": "Delantero",
        "birthday": "06-05-1999",
        "photo": "https://cdn.athletic-club.eus/imagenes/fotofichas/M/javier-marton-anso_M.png",
        "team": 0
    },
    {
        "id": 26,
        "name": "Nicolás",
        "last_name": "Serrano",
        "number": 22,
        "height": 181,
        "country": "España",
        "position": "Delantero",
        "birthday": "05-03-2003",
        "photo": "https://cdn.athletic-club.eus/imagenes/fotofichas/M/nicolas-serrano-galdeano_M.png",
        "team": 0
    },
    {
        "id": 27,
        "name": "Peio",
        "last_name": "Canales",
        "number": 28,
        "height": 179,
        "country": "España",
        "position": "Delantero",
        "birthday": "17-01-2005",
        "photo": "https://cdn.athletic-club.eus/imagenes/fotofichas/M/peio-canales-urtasun_M.png",
        "team": 0
    },
    {
        "id": 28,
        "name": "Juan",
        "last_name": "Musso",
        "number": 1,
        "height": 191,
        "country": "Argentina",
        "position": "Portero",
        "birthday": "06-05-1994",
        "photo": "https://img-estaticos.atleticodemadrid.com/system/fotos/17866/destacado_460x460/jmusso900x900.png?1724774858",
        "team": 1
    },
    {
        "id": 29,
        "name": "Jan",
        "last_name": "Oblak",
        "number": 13,
        "height": 188,
        "country": "Eslovenia",
        "position": "Portero",
        "birthday": "07-01-1993",
        "photo": "https://img-estaticos.atleticodemadrid.com/system/fotos/16531/destacado_460x460/BUSTOS_WEB_900x900_0011_13_OBLAK.png?1723912745",
        "team": 1
    },
    {
        "id": 30,
        "name": "Antonio",
        "last_name": "Gomis",
        "number": 31,
        "height": 186,
        "country": "España",
        "position": "Portero",
        "birthday": "20-05-2003",
        "photo": "https://assets.laliga.com/squad/2024/t175/p493104/256x278/p493104_t175_2024_1_001_000.png",
        "team": 1
    },
    {
        "id": 31,
        "name": "Alejandro",
        "last_name": "Iturbe",
        "number": 33,
        "height": 186,
        "country": "España",
        "position": "Portero",
        "birthday": "02-09-2003",
        "photo": "https://assets.laliga.com/squad/2024/t175/p494920/256x278/p494920_t175_2024_1_001_000.png",
        "team": 1
    },
    {
        "id": 32,
        "name": "José María",
        "last_name": "Giménez",
        "number": 2,
        "height": 185,
        "country": "Uruguay",
        "position": "Defensa",
        "birthday": "20-01-1995",
        "photo": "https://img-estaticos.atleticodemadrid.com/system/fotos/16532/destacado_460x460/BUSTOS_WEB_900x900_0001_2_J-M-GIMENEZ.png?1723912630",
        "team": 1
    },
    {
        "id": 33,
        "name": "César",
        "last_name": "Azpilicueta",
        "number": 3,
        "height": 178,
        "country": "España",
        "position": "Defensa",
        "birthday": "28-08-1989",
        "photo": "https://img-estaticos.atleticodemadrid.com/system/fotos/16549/destacado_460x460/BUSTOS_WEB_900x900_0002_3_AZPILICUETA.png?1723909630",
        "team": 1
    },
    {
        "id": 34,
        "name": "Clément",
        "last_name": "Lenglet",
        "number": 15,
        "height": 186,
        "country": "Francia",
        "position": "Defensa",
        "birthday": "17-06-1995",
        "photo": "https://img-estaticos.atleticodemadrid.com/system/fotos/17864/destacado_460x460/lenglet_900x900.png?1724672851",
        "team": 1
    },
    {
        "id": 35,
        "name": "Nahuel",
        "last_name": "Molina",
        "number": 16,
        "height": 175,
        "country": "Argentina",
        "position": "Defensa",
        "birthday": "06-04-1998",
        "photo": "https://img-estaticos.atleticodemadrid.com/system/fotos/16544/destacado_460x460/BUSTOS_WEB_900x900_0013_16_MOLINA.png?1723910992",
        "team": 1
    },
    {
        "id": 36,
        "name": "Reinildo",
        "last_name": "Isnard",
        "number": 23,
        "height": 180,
        "country": "Mozambique",
        "position": "Defensa",
        "birthday": "21-01-1994",
        "photo": "https://img-estaticos.atleticodemadrid.com/system/fotos/16541/destacado_460x460/BUSTOS_WEB_900x900_0020_23_REINILDO.png?1723910840",
        "team": 1
    },
    {
        "id": 37,
        "name": "Robin",
        "last_name": "Le Normand",
        "number": 24,
        "height": 187,
        "country": "España",
        "position": "Defensa",
        "birthday": "11-11-1996",
        "photo": "https://img-estaticos.atleticodemadrid.com/system/fotos/17831/destacado_460x460/BUSTOS_WEB_900x900_0021_24_LE-NORMAND.png?1723908828",
        "team": 1
    },
    {
        "id": 38,
        "name": "Ilias",
        "last_name": "Kostis",
        "number": 27,
        "height": 188,
        "country": "Grecia",
        "position": "Defensa",
        "birthday": "27-02-2003",
        "photo": "https://assets.laliga.com/squad/2024/t175/p551309/1024x1113/p551309_t175_2024_1_001_000.png",
        "team": 1
    },
    {
        "id": 39,
        "name": "Carlos",
        "last_name": "Gimenez",
        "number": 41,
        "height": 181,
        "country": "España",
        "position": "Defensa",
        "birthday": "18-02-2003",
        "photo": "https://assets.laliga.com/squad/2024/t175/p569933/512x512/p569933_t175_2024_1_004_000.png",
        "team": 1
    },
    {
        "id": 40,
        "name": "Gerónimo",
        "last_name": "Spina",
        "number": 43,
        "height": 187,
        "country": "España",
        "position": "Defensa",
        "birthday": "09-02-2005",
        "photo": "https://assets.laliga.com/squad/2024/t175/p633980/256x278/p633980_t175_2024_1_001_000.png",
        "team": 1
    },
    {
        "id": 41,
        "name": "Conor",
        "last_name": "Gallagher",
        "number": 4,
        "height": 182,
        "country": "Inglaterra",
        "position": "Mediocampista",
        "birthday": "06-02-2000",
        "photo": "https://img-estaticos.atleticodemadrid.com/system/fotos/17861/destacado_460x460/BUSTOS_WEB_900x900_4_GALLAGHER.png?1724317286",
        "team": 1
    },
    {
        "id": 42,
        "name": "Rodrigo",
        "last_name": "De Paul",
        "number": 5,
        "height": 180,
        "country": "Argentina",
        "position": "Mediocampista",
        "birthday": "24-05-1994",
        "photo": "https://img-estaticos.atleticodemadrid.com/system/fotos/16539/destacado_460x460/BUSTOS_WEB_900x900_0003_5_R-DE-PAUL.png?1723911372",
        "team": 1
    },
    {
        "id": 43,
        "name": "Jorge",
        "last_name": "Resurrección",
        "number": 6,
        "height": 176,
        "country": "España",
        "position": "Mediocampista",
        "birthday": "08-01-1992",
        "photo": "https://img-estaticos.atleticodemadrid.com/system/fotos/16530/destacado_460x460/BUSTOS_WEB_900x900_0004_6_KOKE.png?1723913064",
        "team": 1
    },
    {
        "id": 44,
        "name": "Pablo",
        "last_name": "Barrios",
        "number": 8,
        "height": 181,
        "country": "España",
        "position": "Mediocampista",
        "birthday": "15-06-2003",
        "photo": "https://img-estaticos.atleticodemadrid.com/system/fotos/16546/destacado_460x460/BUSTOS_WEB_900x900_0006_8_BARRIOS.png?1723899812",
        "team": 1
    },
    {
        "id": 45,
        "name": "Thomas",
        "last_name": "Lemar",
        "number": 11,
        "height": 171,
        "country": "Francia",
        "position": "Mediocampista",
        "birthday": "12-11-1995",
        "photo": "https://img-estaticos.atleticodemadrid.com/system/fotos/16535/destacado_460x460/BUSTOS_WEB_900x900_0009_11_LEMAR.png?1723912250",
        "team": 1
    },
    {
        "id": 46,
        "name": "Marcos",
        "last_name": "Llorente",
        "number": 14,
        "height": 184,
        "country": "España",
        "position": "Mediocampista",
        "birthday": "30-01-1995",
        "photo": "https://img-estaticos.atleticodemadrid.com/system/fotos/16537/destacado_460x460/BUSTOS_WEB_900x900_0012_14_M-LLORENTE.png?1723911864",
        "team": 1
    },
    {
        "id": 47,
        "name": "Rodrigo",
        "last_name": "Riquelme",
        "number": 17,
        "height": 174,
        "country": "España",
        "position": "Mediocampista",
        "birthday": "02-04-2000",
        "photo": "https://img-estaticos.atleticodemadrid.com/system/fotos/16548/destacado_460x460/BUSTOS_WEB_900x900_0014_17_RIQUELME.png?1723910171",
        "team": 1
    },
    {
        "id": 48,
        "name": "Axel",
        "last_name": "Witsel",
        "number": 20,
        "height": 186,
        "country": "Bélgica",
        "position": "Mediocampista",
        "birthday": "12-01-1989",
        "photo": "https://img-estaticos.atleticodemadrid.com/system/fotos/16545/destacado_460x460/BUSTOS_WEB_900x900_0017_20_WITSEL.png?1723910700",
        "team": 1
    },
    {
        "id": 49,
        "name": "Javier",
        "last_name": "Galán",
        "number": 21,
        "height": 172,
        "country": "España",
        "position": "Mediocampista",
        "birthday": "19-11-1994",
        "photo": "https://img-estaticos.atleticodemadrid.com/system/fotos/17523/destacado_460x460/BUSTOS_WEB_900x900_0022_JAVI-GALAN.png?1723904436",
        "team": 1
    },
    {
        "id": 50,
        "name": "Aitor",
        "last_name": "Gismera",
        "number": 28,
        "height": 182,
        "country": "España",
        "position": "Mediocampista",
        "birthday": "21-02-2004",
        "photo": "https://assets.laliga.com/squad/2024/t175/p493108/256x278/p493108_t175_2024_1_001_000.png",
        "team": 1
    },
    {
        "id": 51,
        "name": "Javier",
        "last_name": "Serrano",
        "number": 29,
        "height": 178,
        "country": "España",
        "position": "Mediocampista",
        "birthday": "16-01-2003",
        "photo": "https://img.uefa.com/imgml/TP/players/1/2025/cutoff/250136445.webp",
        "team": 1
    },
    {
        "id": 52,
        "name": "Antoine",
        "last_name": "Griezmann",
        "number": 7,
        "height": 176,
        "country": "Francia",
        "position": "Delantero",
        "birthday": "21-03-1991",
        "photo": "https://img-estaticos.atleticodemadrid.com/system/fotos/16540/destacado_460x460/BUSTOS_WEB_900x900_0005_7_GRIEZMANN.png?1723911273",
        "team": 1
    },
    {
        "id": 53,
        "name": "Alexander",
        "last_name": "Sørloth",
        "number": 9,
        "height": 195,
        "country": "Noruega",
        "position": "Delantero",
        "birthday": "05-12-1995",
        "photo": "https://img-estaticos.atleticodemadrid.com/system/fotos/17833/destacado_460x460/BUSTOS_WEB_900x900_0007_9_SORLOTH.png?1723908355",
        "team": 1
    },
    {
        "id": 54,
        "name": "Ángel",
        "last_name": "Correa",
        "number": 10,
        "height": 171,
        "country": "Argentina",
        "position": "Delantero",
        "birthday": "09-03-1995",
        "photo": "https://img-estaticos.atleticodemadrid.com/system/fotos/16533/destacado_460x460/BUSTOS_WEB_900x900_0008_10_CORREA.png?1723912394",
        "team": 1
    },
    {
        "id": 55,
        "name": "Samuel",
        "last_name": "Lino",
        "number": 12,
        "height": 170,
        "country": "Brasil",
        "position": "Delantero",
        "birthday": "23-12-1999",
        "photo": "https://img-estaticos.atleticodemadrid.com/system/fotos/16550/destacado_460x460/BUSTOS_WEB_900x900_0010_12_S-LINO.png?1723909316",
        "team": 1
    },
    {
        "id": 56,
        "name": "Julián",
        "last_name": "Álvarez",
        "number": 19,
        "height": 170,
        "country": "Argentina",
        "position": "Delantero",
        "birthday": "31-01-2000",
        "photo": "https://img-estaticos.atleticodemadrid.com/system/fotos/17850/destacado_460x460/BUSTOS_WEB_900x900_0016_19_J-ALVAREZ.png?1723896994",
        "team": 1
    },
    {
        "id": 57,
        "name": "Giuliano",
        "last_name": "Simeone",
        "number": 22,
        "height": 173,
        "country": "Argentina",
        "position": "Delantero",
        "birthday": "18-12-2002",
        "photo": "https://img-estaticos.atleticodemadrid.com/system/fotos/17514/destacado_460x460/BUSTOS_WEB_900x900_0019_22_GIULIANO.png?1723900610",
        "team": 1
    },
    {
        "id": 58,
        "name": "Adrián",
        "last_name": "Niño",
        "number": 32,
        "height": 184,
        "country": "España",
        "position": "Delantero",
        "birthday": "19-06-2004",
        "photo": "https://assets.laliga.com/squad/2024/t175/p593196/256x278/p593196_t175_2024_0_001_000.png",
        "team": 1
    },
    {
        "id": 59,
        "name": "Rayane",
        "last_name": "Belaid",
        "number": 40,
        "height": 174,
        "country": "España",
        "position": "Delantero",
        "birthday": "11-02-2005",
        "photo": "https://assets.laliga.com/squad/2024/t175/p621927/256x278/p621927_t175_2024_0_001_000.png",
        "team": 1
    }
]